{"GlobalPropertiesHash":"Qp3+Tgw1Y5D4TQewLpwRdu/VFxqEcFftWwPuGj7Cs1s=","FingerprintPatternsHash":"gq3WsqcKBUGTSNle7RKKyXRIwh7M8ccEqOqYvIzoM04=","PropertyOverridesHash":"8ZRc1sGeVrPBx4lD717BgRaQekyh78QKV9SKsdt638U=","InputHashes":["pkdT4T\u002BO51/VjVqqcgaqqxov\u002Bjls\u002BafiPkmTaq6/\u002B5U=","jzbn78nx6I4qvO3Vu9AmtAjpARkBuVEDGtjdZ1QqAvo=","1\u002BZRwGiQFsbF3HjsZj0IZWPgvQRHGRxj4UdncrJBqGE=","EqbyU0zGNikCyg5pE47NqlvpUZQm0VPV9SacgyQZD/g=","BRsgshZvPQSPtPAIT/SJRsJFS\u002BGx3/zWbH8E/03wy94=","W2FU1pbR9ocLlH79PpkFAwsmMCZ80JSWTUF6TQUecHg=","0uomuX/Lx\u002BvPxmk3okdwLLLD8snO7cZlJ5JeSzJb\u002BvQ=","w\u002BtAETesO2d4XaS3PDAhkfLOK55jH\u002B4vZh96XOUyxWI=","m99RQf/1b3o5YuFLJoqJ/sd0xAxHAgDZDlPaGnpujHA=","6U\u002BnsCnFPaCvwf6v7YpQ\u002BlOYdjE8mZxJt9WOZg9dmbA=","k9W\u002BjycQ8YQDWSijY/eYqFH0Zyj71BPIqUtKMKGnCh4=","/sNRXDvtywgZgVEylQkDONpZTJGK9snTRNVxjnCFRLY=","qX4xatVnfdYiudfc0Y9d1\u002BbO6ZjmGRFEPpRwgO8GIzY=","dcwSbTYxjkvl1e1kTiJdkvX\u002BDevBo0LBYkn92ImdUUw=","BTnPBGCt8c73YfpMHZkmR46jRIKErHhztsi5Y8Z6ee4=","jReDcQa4L8c/IM/mwPJW1jalV6B8pjwqqW88riES7d8="],"CachedAssets":{"W2FU1pbR9ocLlH79PpkFAwsmMCZ80JSWTUF6TQUecHg=":{"Identity":"C:\\Users\\SoyAlti\\Desktop\\Centrodesalud\\CentroSalud\\CentroSalud.Web\\wwwroot\\js\\medicos.js","SourceId":"CentroSalud.Web","SourceType":"Discovered","ContentRoot":"C:\\Users\\SoyAlti\\Desktop\\Centrodesalud\\CentroSalud\\CentroSalud.Web\\wwwroot\\","BasePath":"/","RelativePath":"js/medicos#[.{fingerprint}]?.js","AssetKind":"All","AssetMode":"All","AssetRole":"Primary","AssetMergeBehavior":null,"AssetMergeSource":"","RelatedAsset":null,"AssetTraitName":null,"AssetTraitValue":null,"Fingerprint":"a5dor6quc9","Integrity":"crRHbLvZXaeNEjtVt9256HRD4hNtFLJdORIiyelMy3c=","CopyToOutputDirectory":"Never","CopyToPublishDirectory":"PreserveNewest","OriginalItemSpec":"wwwroot\\js\\medicos.js","FileLength":2840,"LastWriteTime":"2026-04-23T00:29:28.8548192+00:00"},"k9W\u002BjycQ8YQDWSijY/eYqFH0Zyj71BPIqUtKMKGnCh4=":{"Identity":"C:\\Users\\SoyAlti\\Desktop\\Centrodesalud\\CentroSalud\\CentroSalud.Web\\wwwroot\\pages\\horarios.html","SourceId":"CentroSalud.Web","SourceType":"Discovered","ContentRoot":"C:\\Users\\SoyAlti\\Desktop\\Centrodesalud\\CentroSalud\\CentroSalud.Web\\wwwroot\\","BasePath":"/","RelativePath":"pages/horarios#[.{fingerprint}]?.html","AssetKind":"All","AssetMode":"All","AssetRole":"Primary","AssetMergeBehavior":null,"AssetMergeSource":"","RelatedAsset":null,"AssetTraitName":null,"AssetTraitValue":null,"Fingerprint":"bczk0bcf5p","Integrity":"63uHxzMLSyUwkUTlktAE/h/2MCKjv9kei2acOTifzK0=","CopyToOutputDirectory":"Never","CopyToPublishDirectory":"PreserveNewest","OriginalItemSpec":"wwwroot\\pages\\horarios.html","FileLength":1535,"LastWriteTime":"2026-04-23T00:30:41.4774762+00:00"},"/sNRXDvtywgZgVEylQkDONpZTJGK9snTRNVxjnCFRLY=":{"Identity":"C:\\Users\\SoyAlti\\Desktop\\Centrodesalud\\CentroSalud\\CentroSalud.Web\\wwwroot\\pages\\medicos.html","SourceId":"CentroSalud.Web","SourceType":"Discovered","ContentRoot":"C:\\Users\\SoyAlti\\Desktop\\Centrodesalud\\CentroSalud\\CentroSalud.Web\\wwwroot\\","BasePath":"/","RelativePath":"pages/medicos#[.{fingerprint}]?.html","AssetKind":"All","AssetMode":"All","AssetRole":"Primary","AssetMergeBehavior":null,"AssetMergeSource":"","RelatedAsset":null,"AssetTraitName":null,"AssetTraitValue":null,"Fingerprint":"760uixnoh5","Integrity":"X0JHPWJEqH85yX1EfcUYzwxFS0ISkncy2LfRZWUI96w=","CopyToOutputDirectory":"Never","CopyToPublishDirectory":"PreserveNewest","OriginalItemSpec":"wwwroot\\pages\\medicos.html","FileLength":1039,"LastWriteTime":"2026-04-23T00:23:30.2346632+00:00"},"BRsgshZvPQSPtPAIT/SJRsJFS\u002BGx3/zWbH8E/03wy94=":{"Identity":"C:\\Users\\SoyAlti\\Desktop\\Centrodesalud\\CentroSalud\\CentroSalud.Web\\wwwroot\\js\\horarios.js","SourceId":"CentroSalud.Web","SourceType":"Discovered","ContentRoot":"C:\\Users\\SoyAlti\\Desktop\\Centrodesalud\\CentroSalud\\CentroSalud.Web\\wwwroot\\","BasePath":"/","RelativePath":"js/horarios#[.{fingerprint}]?.js","AssetKind":"All","AssetMode":"All","AssetRole":"Primary","AssetMergeBehavior":null,"AssetMergeSource":"","RelatedAsset":null,"AssetTraitName":null,"AssetTraitValue":null,"Fingerprint":"z5vsr0syc6","Integrity":"OTi5N3bMChKIa6IWmSN74CCotRdv/141I9eku1GMjkk=","CopyToOutputDirectory":"Never","CopyToPublishDirectory":"PreserveNewest","OriginalItemSpec":"wwwroot\\js\\horarios.js","FileLength":3376,"LastWriteTime":"2026-04-23T00:29:36.9584625+00:00"},"dcwSbTYxjkvl1e1kTiJdkvX\u002BDevBo0LBYkn92ImdUUw=":{"Identity":"C:\\Users\\SoyAlti\\Desktop\\Centrodesalud\\CentroSalud\\CentroSalud.Web\\wwwroot\\pages\\vacaciones.html","SourceId":"CentroSalud.Web","SourceType":"Discovered","ContentRoot":"C:\\Users\\SoyAlti\\Desktop\\Centrodesalud\\CentroSalud\\CentroSalud.Web\\wwwroot\\","BasePath":"/","RelativePath":"pages/vacaciones#[.{fingerprint}]?.html","AssetKind":"All","AssetMode":"All","AssetRole":"Primary","AssetMergeBehavior":null,"AssetMergeSource":"","RelatedAsset":null,"AssetTraitName":null,"AssetTraitValue":null,"Fingerprint":"p8noiray8n","Integrity":"V7ZCJOxVWAuj15aW43sfxIZP0\u002BKU5uo6v8nLpG2BIvk=","CopyToOutputDirectory":"Never","CopyToPublishDirectory":"PreserveNewest","OriginalItemSpec":"wwwroot\\pages\\vacaciones.html","FileLength":1018,"LastWriteTime":"2026-04-23T01:02:40.9518952+00:00"},"jzbn78nx6I4qvO3Vu9AmtAjpARkBuVEDGtjdZ1QqAvo=":{"Identity":"C:\\Users\\SoyAlti\\Desktop\\Centrodesalud\\CentroSalud\\CentroSalud.Web\\wwwroot\\index.html","SourceId":"CentroSalud.Web","SourceType":"Discovered","ContentRoot":"C:\\Users\\SoyAlti\\Desktop\\Centrodesalud\\CentroSalud\\CentroSalud.Web\\wwwroot\\","BasePath":"/","RelativePath":"index#[.{fingerprint}]?.html","AssetKind":"All","AssetMode":"All","AssetRole":"Primary","AssetMergeBehavior":null,"AssetMergeSource":"","RelatedAsset":null,"AssetTraitName":null,"AssetTraitValue":null,"Fingerprint":"0zkan5ayvb","Integrity":"rFMQ1L/OiJw0QF5oknJXvwQHH98PKgBEhl/BOw7LzFE=","CopyToOutputDirectory":"Never","CopyToPublishDirectory":"PreserveNewest","OriginalItemSpec":"wwwroot\\index.html","FileLength":415,"LastWriteTime":"2026-04-23T00:39:46.0311443+00:00"},"pkdT4T\u002BO51/VjVqqcgaqqxov\u002Bjls\u002BafiPkmTaq6/\u002B5U=":{"Identity":"C:\\Users\\SoyAlti\\Desktop\\Centrodesalud\\CentroSalud\\CentroSalud.Web\\wwwroot\\css\\styles.css","SourceId":"CentroSalud.Web","SourceType":"Discovered","ContentRoot":"C:\\Users\\SoyAlti\\Desktop\\Centrodesalud\\CentroSalud\\CentroSalud.Web\\wwwroot\\","BasePath":"/","RelativePath":"css/styles#[.{fingerprint}]?.css","AssetKind":"All","AssetMode":"All","AssetRole":"Primary","AssetMergeBehavior":null,"AssetMergeSource":"","RelatedAsset":null,"AssetTraitName":null,"AssetTraitValue":null,"Fingerprint":"0cb0xiulzl","Integrity":"oF1cX/PHEv2EzOWg1yt74fbJ9tXRmB3GpEKSyeXQhF0=","CopyToOutputDirectory":"Never","CopyToPublishDirectory":"PreserveNewest","OriginalItemSpec":"wwwroot\\css\\styles.css","FileLength":431,"LastWriteTime":"2026-04-23T00:38:35.7358571+00:00"},"0uomuX/Lx\u002BvPxmk3okdwLLLD8snO7cZlJ5JeSzJb\u002BvQ=":{"Identity":"C:\\Users\\SoyAlti\\Desktop\\Centrodesalud\\CentroSalud\\CentroSalud.Web\\wwwroot\\js\\pacientes.js","SourceId":"CentroSalud.Web","SourceType":"Discovered","ContentRoot":"C:\\Users\\SoyAlti\\Desktop\\Centrodesalud\\CentroSalud\\CentroSalud.Web\\wwwroot\\","BasePath":"/","RelativePath":"js/pacientes#[.{fingerprint}]?.js","AssetKind":"All","AssetMode":"All","AssetRole":"Primary","AssetMergeBehavior":null,"AssetMergeSource":"","RelatedAsset":null,"AssetTraitName":null,"AssetTraitValue":null,"Fingerprint":"vuywbtyu0b","Integrity":"d5d94UZSnTFtFAU/qo\u002B143i6HriVbrDQEvV6LJJBwYE=","CopyToOutputDirectory":"Never","CopyToPublishDirectory":"PreserveNewest","OriginalItemSpec":"wwwroot\\js\\pacientes.js","FileLength":3894,"LastWriteTime":"2026-04-23T00:47:47.4008228+00:00"},"qX4xatVnfdYiudfc0Y9d1\u002BbO6ZjmGRFEPpRwgO8GIzY=":{"Identity":"C:\\Users\\SoyAlti\\Desktop\\Centrodesalud\\CentroSalud\\CentroSalud.Web\\wwwroot\\pages\\pacientes.html","SourceId":"CentroSalud.Web","SourceType":"Discovered","ContentRoot":"C:\\Users\\SoyAlti\\Desktop\\Centrodesalud\\CentroSalud\\CentroSalud.Web\\wwwroot\\","BasePath":"/","RelativePath":"pages/pacientes#[.{fingerprint}]?.html","AssetKind":"All","AssetMode":"All","AssetRole":"Primary","AssetMergeBehavior":null,"AssetMergeSource":"","RelatedAsset":null,"AssetTraitName":null,"AssetTraitValue":null,"Fingerprint":"r93kgqljr2","Integrity":"cepET0V8A2vC4gwadS\u002BrMLvo9YCF2zxXZBfGjpY\u002B9nY=","CopyToOutputDirectory":"Never","CopyToPublishDirectory":"PreserveNewest","OriginalItemSpec":"wwwroot\\pages\\pacientes.html","FileLength":1047,"LastWriteTime":"2026-04-23T00:47:39.4998489+00:00"},"EqbyU0zGNikCyg5pE47NqlvpUZQm0VPV9SacgyQZD/g=":{"Identity":"C:\\Users\\SoyAlti\\Desktop\\Centrodesalud\\CentroSalud\\CentroSalud.Web\\wwwroot\\js\\empleados.js","SourceId":"CentroSalud.Web","SourceType":"Discovered","ContentRoot":"C:\\Users\\SoyAlti\\Desktop\\Centrodesalud\\CentroSalud\\CentroSalud.Web\\wwwroot\\","BasePath":"/","RelativePath":"js/empleados#[.{fingerprint}]?.js","AssetKind":"All","AssetMode":"All","AssetRole":"Primary","AssetMergeBehavior":null,"AssetMergeSource":"","RelatedAsset":null,"AssetTraitName":null,"AssetTraitValue":null,"Fingerprint":"1wa9nkifmz","Integrity":"nznwJMITQo2KnNIh7L98RXCidl/N/lf02wp3myMIIZM=","CopyToOutputDirectory":"Never","CopyToPublishDirectory":"PreserveNewest","OriginalItemSpec":"wwwroot\\js\\empleados.js","FileLength":3214,"LastWriteTime":"2026-04-23T00:50:36.7531772+00:00"},"6U\u002BnsCnFPaCvwf6v7YpQ\u002BlOYdjE8mZxJt9WOZg9dmbA=":{"Identity":"C:\\Users\\SoyAlti\\Desktop\\Centrodesalud\\CentroSalud\\CentroSalud.Web\\wwwroot\\pages\\empleados.html","SourceId":"CentroSalud.Web","SourceType":"Discovered","ContentRoot":"C:\\Users\\SoyAlti\\Desktop\\Centrodesalud\\CentroSalud\\CentroSalud.Web\\wwwroot\\","BasePath":"/","RelativePath":"pages/empleados#[.{fingerprint}]?.html","AssetKind":"All","AssetMode":"All","AssetRole":"Primary","AssetMergeBehavior":null,"AssetMergeSource":"","RelatedAsset":null,"AssetTraitName":null,"AssetTraitValue":null,"Fingerprint":"aa6afcrnfj","Integrity":"Us3wBoE1WkUwhShvUL2Y9kEiZKatmRpK73TNFLBr64M=","CopyToOutputDirectory":"Never","CopyToPublishDirectory":"PreserveNewest","OriginalItemSpec":"wwwroot\\pages\\empleados.html","FileLength":1031,"LastWriteTime":"2026-04-23T00:50:44.2089492+00:00"},"m99RQf/1b3o5YuFLJoqJ/sd0xAxHAgDZDlPaGnpujHA=":{"Identity":"C:\\Users\\SoyAlti\\Desktop\\Centrodesalud\\CentroSalud\\CentroSalud.Web\\wwwroot\\menu.html","SourceId":"CentroSalud.Web","SourceType":"Discovered","ContentRoot":"C:\\Users\\SoyAlti\\Desktop\\Centrodesalud\\CentroSalud\\CentroSalud.Web\\wwwroot\\","BasePath":"/","RelativePath":"menu#[.{fingerprint}]?.html","AssetKind":"All","AssetMode":"All","AssetRole":"Primary","AssetMergeBehavior":null,"AssetMergeSource":"","RelatedAsset":null,"AssetTraitName":null,"AssetTraitValue":null,"Fingerprint":"e3rwx3zoby","Integrity":"Ki5tvefKvlZB81/v56UaUwA24v\u002BcBN3SvRTIpy2OWsk=","CopyToOutputDirectory":"Never","CopyToPublishDirectory":"PreserveNewest","OriginalItemSpec":"wwwroot\\menu.html","FileLength":644,"LastWriteTime":"2026-04-23T00:56:14.7722572+00:00"},"1\u002BZRwGiQFsbF3HjsZj0IZWPgvQRHGRxj4UdncrJBqGE=":{"Identity":"C:\\Users\\SoyAlti\\Desktop\\Centrodesalud\\CentroSalud\\CentroSalud.Web\\wwwroot\\js\\data.js","SourceId":"CentroSalud.Web","SourceType":"Discovered","ContentRoot":"C:\\Users\\SoyAlti\\Desktop\\Centrodesalud\\CentroSalud\\CentroSalud.Web\\wwwroot\\","BasePath":"/","RelativePath":"js/data#[.{fingerprint}]?.js","AssetKind":"All","AssetMode":"All","AssetRole":"Primary","AssetMergeBehavior":null,"AssetMergeSource":"","RelatedAsset":null,"AssetTraitName":null,"AssetTraitValue":null,"Fingerprint":"tfoami8tym","Integrity":"Obhqf81p1YtCHVzXgpaqacG8pNw56brxrC2lQhjdArQ=","CopyToOutputDirectory":"Never","CopyToPublishDirectory":"PreserveNewest","OriginalItemSpec":"wwwroot\\js\\data.js","FileLength":328,"LastWriteTime":"2026-04-23T00:57:10.0991246+00:00"},"w\u002BtAETesO2d4XaS3PDAhkfLOK55jH\u002B4vZh96XOUyxWI=":{"Identity":"C:\\Users\\SoyAlti\\Desktop\\Centrodesalud\\CentroSalud\\CentroSalud.Web\\wwwroot\\js\\vacaciones.js","SourceId":"CentroSalud.Web","SourceType":"Discovered","ContentRoot":"C:\\Users\\SoyAlti\\Desktop\\Centrodesalud\\CentroSalud\\CentroSalud.Web\\wwwroot\\","BasePath":"/","RelativePath":"js/vacaciones#[.{fingerprint}]?.js","AssetKind":"All","AssetMode":"All","AssetRole":"Primary","AssetMergeBehavior":null,"AssetMergeSource":"","RelatedAsset":null,"AssetTraitName":null,"AssetTraitValue":null,"Fingerprint":"5iud37r5hb","Integrity":"U9XDqBES\u002BNSinpcRTkoQ8NgzuwKhsBcXBVQ33SZrN5k=","CopyToOutputDirectory":"Never","CopyToPublishDirectory":"PreserveNewest","OriginalItemSpec":"wwwroot\\js\\vacaciones.js","FileLength":2426,"LastWriteTime":"2026-04-23T01:02:06.4395043+00:00"}},"CachedCopyCandidates":{}}